[
  {
    "TEC": 16.570244204018547,
    "F107": 167.9,
    "Dst": -24.0,
    "Time": "00:00:00"
  },
  {
    "TEC": 39.53847919655667,
    "F107": 167.9,
    "Dst": -18.0,
    "Time": "01:00:00"
  },
  {
    "TEC": 61.70260589060308,
    "F107": 167.9,
    "Dst": -17.0,
    "Time": "02:00:00"
  },
  {
    "TEC": 74.37349180327868,
    "F107": 167.9,
    "Dst": -18.0,
    "Time": "03:00:00"
  },
  {
    "TEC": 94.54621832884096,
    "F107": 167.9,
    "Dst": -17.0,
    "Time": "04:00:00"
  },
  {
    "TEC": 99.57579479768786,
    "F107": 167.9,
    "Dst": -19.0,
    "Time": "05:00:00"
  },
  {
    "TEC": 103.99696363636363,
    "F107": 167.9,
    "Dst": -15.0,
    "Time": "06:00:00"
  },
  {
    "TEC": 111.87710866141734,
    "F107": 167.9,
    "Dst": -23.0,
    "Time": "07:00:00"
  },
  {
    "TEC": 125.37108670520232,
    "F107": 167.9,
    "Dst": -29.0,
    "Time": "08:00:00"
  },
  {
    "TEC": 124.35362166666665,
    "F107": 167.9,
    "Dst": -24.0,
    "Time": "09:00:00"
  },
  {
    "TEC": 125.32154426229509,
    "F107": 167.9,
    "Dst": -18.0,
    "Time": "10:00:00"
  },
  {
    "TEC": 119.90088597842835,
    "F107": 167.9,
    "Dst": -32.0,
    "Time": "11:00:00"
  },
  {
    "TEC": 104.24474140752864,
    "F107": 167.9,
    "Dst": -39.0,
    "Time": "12:00:00"
  },
  {
    "TEC": 89.77575,
    "F107": 167.9,
    "Dst": -31.0,
    "Time": "13:00:00"
  },
  {
    "TEC": 66.01828349788435,
    "F107": 167.9,
    "Dst": -13.0,
    "Time": "14:00:00"
  },
  {
    "TEC": 52.53403001364257,
    "F107": 167.9,
    "Dst": -11.0,
    "Time": "15:00:00"
  },
  {
    "TEC": 39.10353698630137,
    "F107": 167.9,
    "Dst": -12.0,
    "Time": "16:00:00"
  },
  {
    "TEC": 32.25047449768161,
    "F107": 167.9,
    "Dst": -9.0,
    "Time": "17:00:00"
  },
  {
    "TEC": 27.988797805642633,
    "F107": 167.9,
    "Dst": -22.0,
    "Time": "18:00:00"
  },
  {
    "TEC": 27.12162015503876,
    "F107": 167.9,
    "Dst": -27.0,
    "Time": "19:00:00"
  },
  {
    "TEC": 22.917464788732392,
    "F107": 167.9,
    "Dst": -26.0,
    "Time": "20:00:00"
  },
  {
    "TEC": 15.734403708987163,
    "F107": 167.9,
    "Dst": -22.0,
    "Time": "21:00:00"
  },
  {
    "TEC": 14.038005698005698,
    "F107": 167.9,
    "Dst": -20.0,
    "Time": "22:00:00"
  },
  {
    "TEC": 12.564093272171252,
    "F107": 167.9,
    "Dst": -18.0,
    "Time": "23:00:00"
  },
  {
    "TEC": 13.24409090909091,
    "F107": 178.53333333333333,
    "Dst": -13.0,
    "Time": "00:00:00"
  }
]